atmodel/__init__.py
atmodel/atmodel.py
atmodel-0.1.0.dist-info/AUTHORS.rst
atmodel-0.1.0.dist-info/LICENSE
atmodel-0.1.0.dist-info/METADATA
atmodel-0.1.0.dist-info/WHEEL
atmodel-0.1.0.dist-info/top_level.txt
atmodel-0.1.0.dist-info/RECORD
