Metadata-Version: 2.1
Name: atmodel
Version: 0.1.0
Summary: Create models with less code.
Home-page: https://github.com/eghuro/atmodel
Author: Alexandr Mansurov
Author-email: alex@eghuro.cz
License: MIT license
Keywords: atmodel
Platform: UNKNOWN
Classifier: Development Status :: 2 - Pre-Alpha
Classifier: Intended Audience :: Developers
Classifier: License :: OSI Approved :: MIT License
Classifier: Natural Language :: English
Classifier: Programming Language :: Python :: 3
Classifier: Programming Language :: Python :: 3.5
Classifier: Programming Language :: Python :: 3.6
Classifier: Programming Language :: Python :: 3.7
Requires-Python: >=3.5
